{
  "data": [
    {
      "author": "nimobo",
      "author_created_utc": 1378389918,
      "author_flair_css_class": null,
      "author_flair_text": null,
      "author_fullname": "t2_d0rgw",
      "created_utc": 1440594479,
      "domain": "bloomberg.com",
      "full_link": "https://www.reddit.com/r/worldnews/comments/3ignzy/apple_loses_german_top_court_case_on/",
      "gilded": 0,
      "id": "3ignzy",
      "is_self": false,
      "media_embed": {},
      "num_comments": 0,
      "over_18": false,
      "permalink": "/r/worldnews/comments/3ignzy/apple_loses_german_top_court_case_on/",
      "retrieved_on": 1443143811,
      "score": 39,
      "secure_media_embed": {},
      "selftext": "",
      "stickied": false,
      "subreddit": "worldnews",
      "subreddit_id": "t5_2qh13",
      "thumbnail": "default",
      "title": "Apple Loses German Top Court Case on Swipe-to-Unlock Patent",
      "url": "http://www.bloomberg.com/news/articles/2015-08-25/apple-loses-german-top-court-case-over-swipe-to-unlock-patent"
    },
    {
      "author": "mortalaa",
      "author_created_utc": 1416922816,
      "author_flair_css_class": null,
      "author_flair_text": null,
      "author_fullname": "t2_jlh5v",
      "created_utc": 1439166034,
      "domain": "beta.trtworld.com",
      "full_link": "https://www.reddit.com/r/worldnews/comments/3geml3/eu_finds_no_evidence_of_illegal_practices_by_apple/",
      "gilded": 0,
      "id": "3geml3",
      "is_self": false,
      "media_embed": {},
      "num_comments": 3,
      "over_18": false,
      "permalink": "/r/worldnews/comments/3geml3/eu_finds_no_evidence_of_illegal_practices_by_apple/",
      "post_hint": "link",
      "preview": {
        "images": [
          {
            "id": "BBlqt9ulvO1QWhtJU5XI3pn0mK4RjI2cR89WYmr_JoQ",
            "resolutions": [
              {
                "height": 50,
                "url": "https://i.redditmedia.com/OVr0l7Rv0Se8zO0RiFECtxL1lQ8AM8MaIpUv0fsNSeM.jpg?fit=crop&amp;crop=faces%2Centropy&amp;arh=2&amp;w=108&amp;s=75e5b7c746565a0a10d573dbf1d9eba5",
                "width": 108
              },
              {
                "height": 101,
                "url": "https://i.redditmedia.com/OVr0l7Rv0Se8zO0RiFECtxL1lQ8AM8MaIpUv0fsNSeM.jpg?fit=crop&amp;crop=faces%2Centropy&amp;arh=2&amp;w=216&amp;s=3d83030c4cf4a98a054c036a2978daa5",
                "width": 216
              },
              {
                "height": 150,
                "url": "https://i.redditmedia.com/OVr0l7Rv0Se8zO0RiFECtxL1lQ8AM8MaIpUv0fsNSeM.jpg?fit=crop&amp;crop=faces%2Centropy&amp;arh=2&amp;w=320&amp;s=b557d6ccf229441388bf87479c222201",
                "width": 320
              },
              {
                "height": 300,
                "url": "https://i.redditmedia.com/OVr0l7Rv0Se8zO0RiFECtxL1lQ8AM8MaIpUv0fsNSeM.jpg?fit=crop&amp;crop=faces%2Centropy&amp;arh=2&amp;w=640&amp;s=38e4dc29d7366b68386b445afb135700",
                "width": 640
              }
            ],
            "source": {
              "height": 408,
              "url": "https://i.redditmedia.com/OVr0l7Rv0Se8zO0RiFECtxL1lQ8AM8MaIpUv0fsNSeM.jpg?s=5e98cf047efcc087b740003786ab916f",
              "width": 870
            },
            "variants": {}
          }
        ]
      },
      "retrieved_on": 1440558486,
      "score": 13,
      "secure_media_embed": {},
      "selftext": "",
      "stickied": false,
      "subreddit": "worldnews",
      "subreddit_id": "t5_2qh13",
      "thumbnail": "http://a.thumbs.redditmedia.com/L_LDu7ZluOkLHM0XlzfT3wWEqHajno_qoor2xO54cd4.jpg",
      "title": "EU finds no evidence of illegal practices by Apple",
      "url": "http://beta.trtworld.com/business/eu-finds-no-evidence-of-illegal-practices-by-apple-5666"
    },
    {
      "author": "scouserdave",
      "author_created_utc": 1375287233,
      "author_flair_css_class": null,
      "author_flair_text": null,
      "author_fullname": "t2_ckvgv",
      "created_utc": 1438673264,
      "domain": "uk.businessinsider.com",
      "full_link": "https://www.reddit.com/r/worldnews/comments/3fq05e/apple_is_in_talks_to_launch_its_own_virtual/",
      "gilded": 0,
      "id": "3fq05e",
      "is_self": false,
      "media_embed": {},
      "num_comments": 0,
      "over_18": false,
      "permalink": "/r/worldnews/comments/3fq05e/apple_is_in_talks_to_launch_its_own_virtual/",
      "post_hint": "link",
      "preview": {
        "images": [
          {
            "id": "NYvtBSVhBXTKYfO8YSsZ1oonlzGiEDUOkzXofnaatCg",
            "resolutions": [
              {
                "height": 54,
                "url": "https://i.redditmedia.com/zyeNh4fUEL2_0haN02FMhRheCokU4jJr2RqmwmHJyS8.jpg?fit=crop&amp;crop=faces%2Centropy&amp;arh=2&amp;w=108&amp;s=faddee286ab72e661d4df1527ba9e56f",
                "width": 108
              },
              {
                "height": 108,
                "url": "https://i.redditmedia.com/zyeNh4fUEL2_0haN02FMhRheCokU4jJr2RqmwmHJyS8.jpg?fit=crop&amp;crop=faces%2Centropy&amp;arh=2&amp;w=216&amp;s=20408f24ffafac608c25f105c2864d85",
                "width": 216
              },
              {
                "height": 160,
                "url": "https://i.redditmedia.com/zyeNh4fUEL2_0haN02FMhRheCokU4jJr2RqmwmHJyS8.jpg?fit=crop&amp;crop=faces%2Centropy&amp;arh=2&amp;w=320&amp;s=e9dd7a8a2d74fde9e48cd95e1cfd0c45",
                "width": 320
              },
              {
                "height": 320,
                "url": "https://i.redditmedia.com/zyeNh4fUEL2_0haN02FMhRheCokU4jJr2RqmwmHJyS8.jpg?fit=crop&amp;crop=faces%2Centropy&amp;arh=2&amp;w=640&amp;s=dd11b1e42d7a18bd4f802c9771b466df",
                "width": 640
              },
              {
                "height": 480,
                "url": "https://i.redditmedia.com/zyeNh4fUEL2_0haN02FMhRheCokU4jJr2RqmwmHJyS8.jpg?fit=crop&amp;crop=faces%2Centropy&amp;arh=2&amp;w=960&amp;s=754b50b01c1dbab4bea9fa84a2e6dac6",
                "width": 960
              },
              {
                "height": 540,
                "url": "https://i.redditmedia.com/zyeNh4fUEL2_0haN02FMhRheCokU4jJr2RqmwmHJyS8.jpg?fit=crop&amp;crop=faces%2Centropy&amp;arh=2&amp;w=1080&amp;s=9f840f7165354bf72c7e19e7a199431a",
                "width": 1080
              }
            ],
            "source": {
              "height": 992,
              "url": "https://i.redditmedia.com/zyeNh4fUEL2_0haN02FMhRheCokU4jJr2RqmwmHJyS8.jpg?s=0a436a71d9583464097bb3722f39870b",
              "width": 1983
            },
            "variants": {}
          }
        ]
      },
      "retrieved_on": 1440570095,
      "score": 10,
      "secure_media_embed": {},
      "selftext": "",
      "stickied": false,
      "subreddit": "worldnews",
      "subreddit_id": "t5_2qh13",
      "thumbnail": "http://b.thumbs.redditmedia.com/rdwlIk_wk1Lc0_cTCS2seem2rbbL7_Ea6RhanDQZUFE.jpg",
      "title": "Apple is in talks to launch its own virtual network service in the US and Europe",
      "url": "http://uk.businessinsider.com/apple-in-talks-to-launch-an-mvno-in-the-us-and-europe-2015-8"
    },
    {
      "author": "HDMIPort",
      "author_created_utc": 1427515316,
      "author_flair_css_class": null,
      "author_flair_text": null,
      "author_fullname": "t2_mjdld",
      "created_utc": 1439132591,
      "domain": "theregister.co.uk",
      "full_link": "https://www.reddit.com/r/worldnews/comments/3gcs0s/former_hp_ceo_and_wannabe_president_wants_apple/",
      "gilded": 0,
      "id": "3gcs0s",
      "is_self": false,
      "link_flair_css_class": "normal",
      "link_flair_text": "Editorialized | US politics",
      "media_embed": {},
      "num_comments": 3,
      "over_18": false,
      "permalink": "/r/worldnews/comments/3gcs0s/former_hp_ceo_and_wannabe_president_wants_apple/",
      "retrieved_on": 1440559349,
      "score": 9,
      "secure_media_embed": {},
      "selftext": "",
      "stickied": false,
      "subreddit": "worldnews",
      "subreddit_id": "t5_2qh13",
      "thumbnail": "default",
      "title": "Former HP CEO and wannabe president wants Apple and Google to give \"every last drop of user information\"",
      "url": "http://www.theregister.co.uk/2015/08/07/fiorina_feds/"
    },
    {
      "author": "gsinghpreet",
      "author_created_utc": 1386395488,
      "author_flair_css_class": null,
      "author_flair_text": null,
      "author_fullname": "t2_e8nbv",
      "created_utc": 1440571646,
      "domain": "reuters.com",
      "full_link": "https://www.reddit.com/r/worldnews/comments/3ifrfm/top_german_court_rejects_apple_touchscreen_patent/",
      "gilded": 0,
      "id": "3ifrfm",
      "is_self": false,
      "link_flair_css_class": "normal",
      "link_flair_text": "Not Appropriate Subreddit",
      "media_embed": {},
      "num_comments": 2,
      "over_18": false,
      "permalink": "/r/worldnews/comments/3ifrfm/top_german_court_rejects_apple_touchscreen_patent/",
      "retrieved_on": 1443143386,
      "score": 5,
      "secure_media_embed": {},
      "selftext": "",
      "stickied": false,
      "subreddit": "worldnews",
      "subreddit_id": "t5_2qh13",
      "thumbnail": "default",
      "title": "Top German court rejects Apple touchscreen patent appeal",
      "url": "http://www.reuters.com/article/2015/08/25/us-apple-patent-idUSKCN0QU24120150825"
    },
    {
      "author": "elusive_newsman",
      "author_created_utc": 1398768119,
      "author_flair_css_class": null,
      "author_flair_text": null,
      "author_fullname": "t2_gcpaa",
      "created_utc": 1438504885,
      "domain": "uk.reuters.com",
      "full_link": "https://www.reddit.com/r/worldnews/comments/3fhrpf/apple_bmw_in_courtship_with_an_eye_on_car/",
      "gilded": 0,
      "id": "3fhrpf",
      "is_self": false,
      "media_embed": {},
      "num_comments": 2,
      "over_18": false,
      "permalink": "/r/worldnews/comments/3fhrpf/apple_bmw_in_courtship_with_an_eye_on_car/",
      "post_hint": "link",
      "preview": {
        "images": [
          {
            "id": "B5bVXLH1Nbp90ElGx5uKVp-bO_6Ik9Do-6DrI89iIQg",
            "resolutions": [
              {
                "height": 90,
                "url": "https://i.redditmedia.com/Y-UYqHd2jJDdyTjRo7Ses3UNFwG1UKvqWbetrXM8NHo.jpg?fit=crop&amp;crop=faces%2Centropy&amp;arh=2&amp;w=108&amp;s=941f919443d6bb1507fc0605557e5563",
                "width": 108
              },
              {
                "height": 180,
                "url": "https://i.redditmedia.com/Y-UYqHd2jJDdyTjRo7Ses3UNFwG1UKvqWbetrXM8NHo.jpg?fit=crop&amp;crop=faces%2Centropy&amp;arh=2&amp;w=216&amp;s=c40dcabf071fe9400674f42b2026f6de",
                "width": 216
              }
            ],
            "source": {
              "height": 250,
              "url": "https://i.redditmedia.com/Y-UYqHd2jJDdyTjRo7Ses3UNFwG1UKvqWbetrXM8NHo.jpg?s=43d5884a3ee58f71fd9da84ff8ead8c0",
              "width": 300
            },
            "variants": {}
          }
        ]
      },
      "retrieved_on": 1440573998,
      "score": 5,
      "secure_media_embed": {},
      "selftext": "",
      "stickied": false,
      "subreddit": "worldnews",
      "subreddit_id": "t5_2qh13",
      "thumbnail": "http://b.thumbs.redditmedia.com/kOdv-gsVhItJRXFuJJlpz1uq8r26Q4-fvWaxCuKTB7M.jpg",
      "title": "Apple, BMW in courtship with an eye on car collaboration",
      "url": "http://uk.reuters.com/article/2015/08/02/apple-bmw-courtship-idUKL5N10B50720150802"
    },
    {
      "author": "ruddigerD",
      "author_created_utc": 1372864631,
      "author_flair_css_class": null,
      "author_flair_text": null,
      "author_fullname": "t2_c910t",
      "created_utc": 1439301613,
      "domain": "bits.blogs.nytimes.com",
      "full_link": "https://www.reddit.com/r/worldnews/comments/3gld8w/nebia_a_shower_head_startup_receives_funding_from/",
      "gilded": 0,
      "id": "3gld8w",
      "is_self": false,
      "media_embed": {},
      "num_comments": 2,
      "over_18": false,
      "permalink": "/r/worldnews/comments/3gld8w/nebia_a_shower_head_startup_receives_funding_from/",
      "retrieved_on": 1440555281,
      "score": 4,
      "secure_media_embed": {},
      "selftext": "",
      "stickied": false,
      "subreddit": "worldnews",
      "subreddit_id": "t5_2qh13",
      "thumbnail": "default",
      "title": "Nebia, a Shower Head Start-Up, Receives Funding From Apple CEO Tim Cook",
      "url": "http://bits.blogs.nytimes.com/2015/08/11/nebia-a-shower-head-start-up-gets-funded-by-apple-ceo-cook/?_r=1"
    },
    {
      "author": "Huboftrends",
      "author_created_utc": 1440483849,
      "author_flair_css_class": null,
      "author_flair_text": null,
      "author_fullname": "t2_pu8sg",
      "created_utc": 1440755190,
      "domain": "largecapture.com",
      "full_link": "https://www.reddit.com/r/worldnews/comments/3ipijp/apple_shares_plummet_despite_ceo_tim_cook_claim/",
      "gilded": 0,
      "id": "3ipijp",
      "is_self": false,
      "media_embed": {},
      "num_comments": 6,
      "over_18": false,
      "permalink": "/r/worldnews/comments/3ipijp/apple_shares_plummet_despite_ceo_tim_cook_claim/",
      "retrieved_on": 1443147991,
      "score": 4,
      "secure_media_embed": {},
      "selftext": "",
      "stickied": false,
      "subreddit": "worldnews",
      "subreddit_id": "t5_2qh13",
      "thumbnail": "default",
      "title": "Apple Shares Plummet Despite CEO Tim Cook Claim China iPhone Sales Are Great.",
      "url": "http://www.largecapture.com/2015/08/apple-inc-aapl-shares-plummet-despite.html"
    },
    {
      "author": "madam1",
      "author_created_utc": 1240855325,
      "author_flair_css_class": null,
      "author_flair_text": null,
      "author_fullname": "t2_3gm46",
      "created_utc": 1439597909,
      "domain": "theguardian.com",
      "full_link": "https://www.reddit.com/r/worldnews/comments/3h1k3v/apple_is_building_a_selfdriving_car_in_silicon/",
      "gilded": 0,
      "id": "3h1k3v",
      "is_self": false,
      "link_flair_css_class": "normal",
      "link_flair_text": "US internal news",
      "media_embed": {},
      "num_comments": 2,
      "over_18": false,
      "permalink": "/r/worldnews/comments/3h1k3v/apple_is_building_a_selfdriving_car_in_silicon/",
      "retrieved_on": 1440547532,
      "score": 3,
      "secure_media_embed": {},
      "selftext": "",
      "stickied": false,
      "subreddit": "worldnews",
      "subreddit_id": "t5_2qh13",
      "thumbnail": "default",
      "title": "Apple is building a self-driving car in Silicon Valley, and is scouting for secure locations in the San Francisco Bay area to test it, the Guardian has learned. Documents show the oft-rumoured Apple car project appears to be further along than many suspected.",
      "url": "http://www.theguardian.com/technology/2015/aug/14/apple-self-driving-car-project-titan-sooner-than-expected"
    },
    {
      "author": "[deleted]",
      "author_flair_css_class": null,
      "author_flair_text": null,
      "created_utc": 1439578892,
      "domain": "gu.com",
      "full_link": "https://www.reddit.com/r/worldnews/comments/3h0dk9/documents_confirm_apple_is_building_selfdriving/",
      "gilded": 0,
      "id": "3h0dk9",
      "is_self": false,
      "media_embed": {},
      "num_comments": 4,
      "over_18": false,
      "permalink": "/r/worldnews/comments/3h0dk9/documents_confirm_apple_is_building_selfdriving/",
      "retrieved_on": 1440548083,
      "score": 3,
      "secure_media_embed": {},
      "selftext": "",
      "stickied": false,
      "subreddit": "worldnews",
      "subreddit_id": "t5_2qh13",
      "thumbnail": "default",
      "title": "Documents confirm Apple is building self-driving car",
      "url": "http://gu.com/p/4bhv8?CMP=Share_AndroidApp_BaconReader"
    },
    {
      "author": "Wowza-yowza",
      "author_created_utc": 1438107465,
      "author_flair_css_class": null,
      "author_flair_text": null,
      "author_fullname": "t2_p50wl",
      "created_utc": 1438646286,
      "domain": "msn.com",
      "full_link": "https://www.reddit.com/r/worldnews/comments/3fon6r/apple_looking_into_starting_its_own_wireless/",
      "gilded": 0,
      "id": "3fon6r",
      "is_self": false,
      "media_embed": {},
      "num_comments": 4,
      "over_18": false,
      "permalink": "/r/worldnews/comments/3fon6r/apple_looking_into_starting_its_own_wireless/",
      "post_hint": "link",
      "preview": {
        "images": [
          {
            "id": "KIzxTZg6Z3Yay4akJaliZfV8UGphr0hJ694SycbbxAs",
            "resolutions": [
              {
                "height": 81,
                "url": "https://i.redditmedia.com/1o5oo8yLriF35ZqvVxkkGUOqrliQPce4ZHLBaw19Hjo.jpg?fit=crop&amp;crop=faces%2Centropy&amp;arh=2&amp;w=108&amp;s=a8e190d6429e7987e78ee56395c1b23d",
                "width": 108
              },
              {
                "height": 162,
                "url": "https://i.redditmedia.com/1o5oo8yLriF35ZqvVxkkGUOqrliQPce4ZHLBaw19Hjo.jpg?fit=crop&amp;crop=faces%2Centropy&amp;arh=2&amp;w=216&amp;s=a860ea4377144e516107b4b3332f0fd1",
                "width": 216
              }
            ],
            "source": {
              "height": 225,
              "url": "https://i.redditmedia.com/1o5oo8yLriF35ZqvVxkkGUOqrliQPce4ZHLBaw19Hjo.jpg?s=a4c2bde7d24a2e032d93b5aee11d19be",
              "width": 300
            },
            "variants": {}
          }
        ]
      },
      "retrieved_on": 1440570730,
      "score": 3,
      "secure_media_embed": {},
      "selftext": "",
      "stickied": false,
      "subreddit": "worldnews",
      "subreddit_id": "t5_2qh13",
      "thumbnail": "http://b.thumbs.redditmedia.com/XzaiMfQNP3dNodQkB0PyS7PrnSa3gXXqOg1T9ViEf4k.jpg",
      "title": "Apple looking into starting its own wireless service",
      "url": "http://www.msn.com/en-us/news/technology/apple-in-talks-to-launch-its-own-wireless-service/ar-BBlmjuZ?ocid=spartandhp"
    },
    {
      "author": "deadlypies",
      "author_created_utc": 1427052752,
      "author_flair_css_class": null,
      "author_flair_text": null,
      "author_fullname": "t2_mf8ai",
      "created_utc": 1440377054,
      "domain": "money.cnn.com",
      "full_link": "https://www.reddit.com/r/worldnews/comments/3i55uf/apple_recalling_iphone_6_plus_after_camera/",
      "gilded": 0,
      "id": "3i55uf",
      "is_self": false,
      "link_flair_css_class": "normal",
      "link_flair_text": "Not Appropriate Subreddit",
      "media_embed": {},
      "num_comments": 0,
      "over_18": false,
      "permalink": "/r/worldnews/comments/3i55uf/apple_recalling_iphone_6_plus_after_camera/",
      "retrieved_on": 1440528754,
      "score": 2,
      "secure_media_embed": {},
      "selftext": "",
      "stickied": false,
      "subreddit": "worldnews",
      "subreddit_id": "t5_2qh13",
      "thumbnail": "default",
      "title": "Apple Recalling iPhone 6 Plus After Camera Malfunctions",
      "url": "http://money.cnn.com/2015/08/23/technology/apple-iphone-6-plus-camera-recall/index.html"
    },
    {
      "author": "thanaads",
      "author_created_utc": 1203609932,
      "author_flair_css_class": null,
      "author_flair_text": null,
      "author_fullname": "t2_33dkf",
      "created_utc": 1440722184,
      "domain": "iphone.click2creation.com",
      "full_link": "https://www.reddit.com/r/worldnews/comments/3io14b/apple_iphone_event_announced_for_wednesday/",
      "gilded": 0,
      "id": "3io14b",
      "is_self": false,
      "media_embed": {},
      "num_comments": 0,
      "over_18": false,
      "permalink": "/r/worldnews/comments/3io14b/apple_iphone_event_announced_for_wednesday/",
      "retrieved_on": 1443147291,
      "score": 1,
      "secure_media_embed": {},
      "selftext": "",
      "stickied": false,
      "subreddit": "worldnews",
      "subreddit_id": "t5_2qh13",
      "thumbnail": "default",
      "title": "Apple iPhone event announced for Wednesday, September 9",
      "url": "http://iphone.click2creation.com/2015/08/apple-iphone-event-announced-for-wednesday-september-9/"
    },
    {
      "author": "applemactechsuport",
      "author_created_utc": 1440428815,
      "author_flair_css_class": null,
      "author_flair_text": null,
      "author_fullname": "t2_ptkh5",
      "created_utc": 1441052559,
      "domain": "applemactechnicalsupportnumber.blogspot.com",
      "full_link": "https://www.reddit.com/r/worldnews/comments/3j4n5z/apple_mac_mini_technical_support_number/",
      "gilded": 0,
      "id": "3j4n5z",
      "is_self": false,
      "media_embed": {},
      "num_comments": 0,
      "over_18": false,
      "permalink": "/r/worldnews/comments/3j4n5z/apple_mac_mini_technical_support_number/",
      "retrieved_on": 1443155141,
      "score": 1,
      "secure_media_embed": {},
      "selftext": "",
      "stickied": false,
      "subreddit": "worldnews",
      "subreddit_id": "t5_2qh13",
      "thumbnail": "default",
      "title": "Apple Mac Mini Technical Support Number +1-8005069828",
      "url": "http://applemactechnicalsupportnumber.blogspot.com/"
    },
    {
      "author": "applemactechsuport",
      "author_created_utc": 1440428815,
      "author_flair_css_class": null,
      "author_flair_text": null,
      "author_fullname": "t2_ptkh5",
      "created_utc": 1441047949,
      "domain": "mactechnicalsupportphonenumber.wordpress.com",
      "full_link": "https://www.reddit.com/r/worldnews/comments/3j4bj5/apple_mac_mini_tech_support_phone_number/",
      "gilded": 0,
      "id": "3j4bj5",
      "is_self": false,
      "media_embed": {},
      "num_comments": 0,
      "over_18": false,
      "permalink": "/r/worldnews/comments/3j4bj5/apple_mac_mini_tech_support_phone_number/",
      "retrieved_on": 1443154988,
      "score": 1,
      "secure_media_embed": {},
      "selftext": "",
      "stickied": false,
      "subreddit": "worldnews",
      "subreddit_id": "t5_2qh13",
      "thumbnail": "default",
      "title": "Apple Mac Mini Tech Support phone Number- 1-800-506-9828",
      "url": "https://mactechnicalsupportphonenumber.wordpress.com/"
    },
    {
      "author": "applemactechsuport",
      "author_created_utc": 1440428815,
      "author_flair_css_class": null,
      "author_flair_text": null,
      "author_fullname": "t2_ptkh5",
      "created_utc": 1441033022,
      "domain": "applemacsupportnumber.com",
      "full_link": "https://www.reddit.com/r/worldnews/comments/3j3bcv/apple_mac_mini_technical_support_phone_number/",
      "gilded": 0,
      "id": "3j3bcv",
      "is_self": false,
      "media_embed": {},
      "num_comments": 0,
      "over_18": false,
      "permalink": "/r/worldnews/comments/3j3bcv/apple_mac_mini_technical_support_phone_number/",
      "retrieved_on": 1443154514,
      "score": 1,
      "secure_media_embed": {},
      "selftext": "",
      "stickied": false,
      "subreddit": "worldnews",
      "subreddit_id": "t5_2qh13",
      "thumbnail": "default",
      "title": "Apple Mac mini technical support phone number 1-800-506-9828",
      "url": "http://www.applemacsupportnumber.com/mac-mini-support"
    },
    {
      "author": "piyambakan",
      "author_created_utc": 1434808044,
      "author_flair_css_class": null,
      "author_flair_text": null,
      "author_fullname": "t2_o8bxm",
      "created_utc": 1439204499,
      "domain": "piyambakan.info",
      "full_link": "https://www.reddit.com/r/worldnews/comments/3gg9kt/apple_reportedly_will_introduces_several_new/",
      "gilded": 0,
      "id": "3gg9kt",
      "is_self": false,
      "media_embed": {},
      "num_comments": 0,
      "over_18": false,
      "permalink": "/r/worldnews/comments/3gg9kt/apple_reportedly_will_introduces_several_new/",
      "retrieved_on": 1440557721,
      "score": 1,
      "secure_media_embed": {},
      "selftext": "",
      "stickied": false,
      "subreddit": "worldnews",
      "subreddit_id": "t5_2qh13",
      "thumbnail": "default",
      "title": "Apple Reportedly Will Introduces Several New Tools Next Month",
      "url": "http://www.piyambakan.info/2015/08/Apple-Reportedly-Will-Introduces-Several-New-Tools-Next-Month.html"
    },
    {
      "author": "amazoniphone6plus",
      "author_created_utc": 1434793643,
      "author_flair_css_class": null,
      "author_flair_text": null,
      "author_fullname": "t2_o88f5",
      "created_utc": 1439126165,
      "domain": "amazon.com",
      "full_link": "https://www.reddit.com/r/worldnews/comments/3gci5a/apple_iphone_6_plus_case/",
      "gilded": 0,
      "id": "3gci5a",
      "is_self": false,
      "media_embed": {},
      "num_comments": 0,
      "over_18": false,
      "permalink": "/r/worldnews/comments/3gci5a/apple_iphone_6_plus_case/",
      "retrieved_on": 1440559476,
      "score": 1,
      "secure_media_embed": {},
      "selftext": "",
      "stickied": false,
      "subreddit": "worldnews",
      "subreddit_id": "t5_2qh13",
      "thumbnail": "default",
      "title": "Apple iPhone 6 Plus case",
      "url": "http://www.amazon.com/gp/product/B00ZHKJHH0"
    },
    {
      "author": "thana103",
      "author_created_utc": 1246029538,
      "author_flair_css_class": null,
      "author_flair_text": null,
      "author_fullname": "t2_3iyz5",
      "created_utc": 1440473831,
      "domain": "iphone.click2creation.com",
      "full_link": "https://www.reddit.com/r/worldnews/comments/3iafxn/apple_to_replace_some_iphone_cameras_over_photos/",
      "gilded": 0,
      "id": "3iafxn",
      "is_self": false,
      "media_embed": {},
      "num_comments": 0,
      "over_18": false,
      "permalink": "/r/worldnews/comments/3iafxn/apple_to_replace_some_iphone_cameras_over_photos/",
      "retrieved_on": 1440526230,
      "score": 1,
      "secure_media_embed": {},
      "selftext": "",
      "stickied": false,
      "subreddit": "worldnews",
      "subreddit_id": "t5_2qh13",
      "thumbnail": "default",
      "title": "Apple to replace some iPhone cameras over photos",
      "url": "http://iphone.click2creation.com/2015/08/apple-to-replace-some-iphone-cameras-over-photos/"
    },
    {
      "author": "arogyapoint",
      "author_created_utc": 1439493127,
      "author_flair_css_class": null,
      "author_flair_text": null,
      "author_fullname": "t2_pj5xc",
      "created_utc": 1439552361,
      "domain": "arogyapoint.com",
      "full_link": "https://www.reddit.com/r/worldnews/comments/3gyroa/buy_apple_cider_ginger_at_affordable_price/",
      "gilded": 0,
      "id": "3gyroa",
      "is_self": false,
      "media_embed": {},
      "num_comments": 1,
      "over_18": false,
      "permalink": "/r/worldnews/comments/3gyroa/buy_apple_cider_ginger_at_affordable_price/",
      "retrieved_on": 1440548834,
      "score": 1,
      "secure_media_embed": {},
      "selftext": "",
      "stickied": false,
      "subreddit": "worldnews",
      "subreddit_id": "t5_2qh13",
      "thumbnail": "default",
      "title": "Buy Apple Cider Ginger at Affordable Price",
      "url": "http://arogyapoint.com/index.php?route=product/product&amp;path=73_83_93&amp;product_id=104"
    },
    {
      "author": "collagenelife",
      "author_created_utc": 1202532627,
      "author_flair_css_class": null,
      "author_flair_text": null,
      "author_fullname": "t2_333pf",
      "created_utc": 1440249336,
      "domain": "techcrunch.com",
      "full_link": "https://www.reddit.com/r/worldnews/comments/3hys58/dont_be_apple/",
      "gilded": 0,
      "id": "3hys58",
      "is_self": false,
      "media_embed": {},
      "num_comments": 0,
      "over_18": false,
      "permalink": "/r/worldnews/comments/3hys58/dont_be_apple/",
      "retrieved_on": 1440531731,
      "score": 1,
      "secure_media_embed": {},
      "selftext": "",
      "stickied": false,
      "subreddit": "worldnews",
      "subreddit_id": "t5_2qh13",
      "thumbnail": "default",
      "title": "Don\u2019t Be Apple",
      "url": "http://techcrunch.com/2015/08/22/dont-be-apple/"
    },
    {
      "author": "workitloud",
      "author_created_utc": 1328802449,
      "author_flair_css_class": null,
      "author_flair_text": null,
      "author_fullname": "t2_6voxi",
      "created_utc": 1439665083,
      "domain": "techinsider.io",
      "full_link": "https://www.reddit.com/r/worldnews/comments/3h4eui/inside_the_abandoned_military_base_where_apple/",
      "gilded": 0,
      "id": "3h4eui",
      "is_self": false,
      "link_flair_css_class": "normal",
      "link_flair_text": "Not Appropriate Subreddit",
      "media_embed": {},
      "num_comments": 0,
      "over_18": false,
      "permalink": "/r/worldnews/comments/3h4eui/inside_the_abandoned_military_base_where_apple/",
      "retrieved_on": 1440546141,
      "score": 1,
      "secure_media_embed": {},
      "selftext": "",
      "stickied": false,
      "subreddit": "worldnews",
      "subreddit_id": "t5_2qh13",
      "thumbnail": "default",
      "title": "Inside the abandoned military base where Apple reportedly wants to test its top-secret car",
      "url": "http://www.techinsider.io/inside-the-gomentum-station-2015-8"
    },
    {
      "author": "gurpiyar",
      "author_created_utc": 1217401351,
      "author_flair_css_class": null,
      "author_flair_text": null,
      "author_fullname": "t2_37gwm",
      "created_utc": 1439729519,
      "domain": "youtube.com",
      "full_link": "https://www.reddit.com/r/worldnews/comments/3h72ea/apple_fruit_nutritional_value_of_apples_health/",
      "gilded": 0,
      "id": "3h72ea",
      "is_self": false,
      "link_flair_css_class": "normal",
      "link_flair_text": "No videos",
      "media_embed": {},
      "num_comments": 0,
      "over_18": false,
      "permalink": "/r/worldnews/comments/3h72ea/apple_fruit_nutritional_value_of_apples_health/",
      "retrieved_on": 1440544902,
      "score": 1,
      "secure_media_embed": {},
      "selftext": "",
      "stickied": false,
      "subreddit": "worldnews",
      "subreddit_id": "t5_2qh13",
      "thumbnail": "default",
      "title": "Apple Fruit Nutritional Value of Apples Health Benefits",
      "url": "https://www.youtube.com/attribution_link?a=8UkcWaBVb4k&amp;u=%2Fwatch%3Fv%3Dls59ilMGW_8%26feature%3Dshare"
    },
    {
      "author": "applemactech",
      "author_created_utc": 1440517834,
      "author_flair_css_class": null,
      "author_flair_text": null,
      "author_fullname": "t2_pukuz",
      "created_utc": 1440523968,
      "domain": "manta.com",
      "full_link": "https://www.reddit.com/r/worldnews/comments/3icw90/apple_customer_support_phone_number/",
      "gilded": 0,
      "id": "3icw90",
      "is_self": false,
      "media_embed": {},
      "num_comments": 1,
      "over_18": false,
      "permalink": "/r/worldnews/comments/3icw90/apple_customer_support_phone_number/",
      "retrieved_on": 1440525085,
      "score": 1,
      "secure_media_embed": {},
      "selftext": "",
      "stickied": false,
      "subreddit": "worldnews",
      "subreddit_id": "t5_2qh13",
      "thumbnail": "default",
      "title": "Apple Customer Support Phone Number",
      "url": "http://www.manta.com/c/mx5mmxf/apple-mac-technical-support-phone-number-1-800-506-9828"
    },
    {
      "author": "[deleted]",
      "author_flair_css_class": null,
      "author_flair_text": null,
      "created_utc": 1438612783,
      "domain": "belfasttelegraph.co.uk",
      "full_link": "https://www.reddit.com/r/worldnews/comments/3fmgv2/apple_car_visit_to_bmw_factory_fuels_further/",
      "gilded": 0,
      "id": "3fmgv2",
      "is_self": false,
      "media_embed": {},
      "num_comments": 0,
      "over_18": false,
      "permalink": "/r/worldnews/comments/3fmgv2/apple_car_visit_to_bmw_factory_fuels_further/",
      "retrieved_on": 1440571806,
      "score": 1,
      "secure_media_embed": {},
      "selftext": "",
      "stickied": false,
      "subreddit": "worldnews",
      "subreddit_id": "t5_2qh13",
      "thumbnail": "default",
      "title": "Apple car: Visit to BMW factory fuels further rumours of possible partnership",
      "url": "http://www.belfasttelegraph.co.uk/technology/apple-car-visit-to-bmw-factory-fuels-further-rumours-of-possible-partnership-31423855.html"
    },
    {
      "author": "amazoniphone6",
      "author_created_utc": 1434787383,
      "author_flair_css_class": null,
      "author_flair_text": null,
      "author_fullname": "t2_o86zr",
      "created_utc": 1439664167,
      "domain": "plurk.com",
      "full_link": "https://www.reddit.com/r/worldnews/comments/3h4d0v/apple_iphone_6_cover/",
      "gilded": 0,
      "id": "3h4d0v",
      "is_self": false,
      "media_embed": {},
      "num_comments": 0,
      "over_18": false,
      "permalink": "/r/worldnews/comments/3h4d0v/apple_iphone_6_cover/",
      "retrieved_on": 1440546164,
      "score": 1,
      "secure_media_embed": {},
      "selftext": "",
      "stickied": false,
      "subreddit": "worldnews",
      "subreddit_id": "t5_2qh13",
      "thumbnail": "default",
      "title": "Apple iPhone 6 cover",
      "url": "https://www.plurk.com/p/l5vk15"
    },
    {
      "author": "inet",
      "author_created_utc": 1152611388,
      "author_flair_css_class": null,
      "author_flair_text": null,
      "author_fullname": "t2_9s4c",
      "created_utc": 1440073288,
      "domain": "thenational.ae",
      "full_link": "https://www.reddit.com/r/worldnews/comments/3hplo8/apple_granted_exemption_from_uae_foreign/",
      "gilded": 0,
      "id": "3hplo8",
      "is_self": false,
      "media_embed": {},
      "num_comments": 1,
      "over_18": false,
      "permalink": "/r/worldnews/comments/3hplo8/apple_granted_exemption_from_uae_foreign/",
      "post_hint": "link",
      "preview": {
        "images": [
          {
            "id": "c4lkNyWglShzqnix-W47dIJS2XQR3WhpFIcrDojvXFY",
            "resolutions": [
              {
                "height": 72,
                "url": "https://i.redditmedia.com/eRO1ugnMC3Qa37pBy2JQDNLlRG3qDTiznFwA2MxWE2w.jpg?fit=crop&amp;crop=faces%2Centropy&amp;arh=2&amp;w=108&amp;s=6df751f3bf2c089a1b3d55649759ab60",
                "width": 108
              },
              {
                "height": 144,
                "url": "https://i.redditmedia.com/eRO1ugnMC3Qa37pBy2JQDNLlRG3qDTiznFwA2MxWE2w.jpg?fit=crop&amp;crop=faces%2Centropy&amp;arh=2&amp;w=216&amp;s=d8e5051391e73f915623696742c64a66",
                "width": 216
              },
              {
                "height": 213,
                "url": "https://i.redditmedia.com/eRO1ugnMC3Qa37pBy2JQDNLlRG3qDTiznFwA2MxWE2w.jpg?fit=crop&amp;crop=faces%2Centropy&amp;arh=2&amp;w=320&amp;s=a31cf9cc70d01a2684aaecf78d485a96",
                "width": 320
              },
              {
                "height": 426,
                "url": "https://i.redditmedia.com/eRO1ugnMC3Qa37pBy2JQDNLlRG3qDTiznFwA2MxWE2w.jpg?fit=crop&amp;crop=faces%2Centropy&amp;arh=2&amp;w=640&amp;s=31b270c7710e04a7c1f150b902574f15",
                "width": 640
              },
              {
                "height": 640,
                "url": "https://i.redditmedia.com/eRO1ugnMC3Qa37pBy2JQDNLlRG3qDTiznFwA2MxWE2w.jpg?fit=crop&amp;crop=faces%2Centropy&amp;arh=2&amp;w=960&amp;s=be707866d559f4486fa57a19cb493a84",
                "width": 960
              }
            ],
            "source": {
              "height": 683,
              "url": "https://i.redditmedia.com/eRO1ugnMC3Qa37pBy2JQDNLlRG3qDTiznFwA2MxWE2w.jpg?s=514f1719b69e4c0ba372c71c08ed5c9f",
              "width": 1024
            },
            "variants": {}
          }
        ]
      },
      "retrieved_on": 1440536133,
      "score": 1,
      "secure_media_embed": {},
      "selftext": "",
      "stickied": false,
      "subreddit": "worldnews",
      "subreddit_id": "t5_2qh13",
      "thumbnail": "http://b.thumbs.redditmedia.com/l4TULlvNt1K2fPDQkV3nMODFR3fonG7GhGUsKL4somE.jpg",
      "title": "Apple granted exemption from UAE foreign ownership laws. Under local regulations, all businesses operating in the UAE must be 51 per cent owned by Emiratis",
      "url": "http://www.thenational.ae/business/retail/apple-granted-exemption-from-uae-foreign-ownership-laws-sources-say"
    },
    {
      "author": "[deleted]",
      "author_flair_css_class": null,
      "author_flair_text": null,
      "created_utc": 1439582771,
      "domain": "businessinsider.com",
      "full_link": "https://www.reddit.com/r/worldnews/comments/3h0mvh/leaked_documents_prove_that_apple_is_already/",
      "gilded": 0,
      "id": "3h0mvh",
      "is_self": false,
      "media_embed": {},
      "num_comments": 6,
      "over_18": false,
      "permalink": "/r/worldnews/comments/3h0mvh/leaked_documents_prove_that_apple_is_already/",
      "retrieved_on": 1440547963,
      "score": 1,
      "secure_media_embed": {},
      "selftext": "",
      "stickied": false,
      "subreddit": "worldnews",
      "subreddit_id": "t5_2qh13",
      "thumbnail": "default",
      "title": "Leaked documents prove that Apple is already testing it's self-driving car.",
      "url": "http://www.businessinsider.com/apple-car-rumors-2015-8"
    },
    {
      "author": "affordablemac",
      "author_created_utc": 1421495472,
      "author_flair_css_class": null,
      "author_flair_text": null,
      "author_fullname": "t2_kroch",
      "created_utc": 1438603865,
      "domain": "affordablemac.co.uk",
      "full_link": "https://www.reddit.com/r/worldnews/comments/3fm0o5/refurbished_apple_mac_affordable_mac/",
      "gilded": 0,
      "id": "3fm0o5",
      "is_self": false,
      "media_embed": {},
      "num_comments": 0,
      "over_18": false,
      "permalink": "/r/worldnews/comments/3fm0o5/refurbished_apple_mac_affordable_mac/",
      "retrieved_on": 1440572016,
      "score": 1,
      "secure_media_embed": {},
      "selftext": "",
      "stickied": false,
      "subreddit": "worldnews",
      "subreddit_id": "t5_2qh13",
      "thumbnail": "default",
      "title": "Refurbished Apple Mac - Affordable Mac",
      "url": "http://www.affordablemac.co.uk/refurbished-apple-mac-the-salience-of-extended-power-lifespan-of-mac-system"
    },
    {
      "author": "libertyissues",
      "author_created_utc": 1424692098,
      "author_flair_css_class": null,
      "author_flair_text": null,
      "author_fullname": "t2_lje7c",
      "created_utc": 1438889012,
      "domain": "voicesofliberty.com",
      "full_link": "https://www.reddit.com/r/worldnews/comments/3g1gxh/freak_security_flaw_hits_android_apple_users/",
      "gilded": 0,
      "id": "3g1gxh",
      "is_self": false,
      "media_embed": {},
      "num_comments": 0,
      "over_18": false,
      "permalink": "/r/worldnews/comments/3g1gxh/freak_security_flaw_hits_android_apple_users/",
      "retrieved_on": 1440564743,
      "score": 1,
      "secure_media_embed": {},
      "selftext": "",
      "stickied": false,
      "subreddit": "worldnews",
      "subreddit_id": "t5_2qh13",
      "thumbnail": "default",
      "title": "FREAK Security Flaw Hits Android, Apple Users Because Government",
      "url": "http://www.voicesofliberty.com/article/freak-security-flaw-hits-android-apple-users-because-government/?utm_source=reddit&amp;utm_campaign=DSK"
    },
    {
      "author": "applemactechsuport",
      "author_created_utc": 1440428815,
      "author_flair_css_class": null,
      "author_flair_text": null,
      "author_fullname": "t2_ptkh5",
      "created_utc": 1441048808,
      "domain": "applemactechsupportphonenumber.tumblr.com",
      "full_link": "https://www.reddit.com/r/worldnews/comments/3j4dpa/apple_mac_technical_support_phone/",
      "gilded": 0,
      "id": "3j4dpa",
      "is_self": false,
      "media_embed": {},
      "num_comments": 0,
      "over_18": false,
      "permalink": "/r/worldnews/comments/3j4dpa/apple_mac_technical_support_phone/",
      "retrieved_on": 1443155016,
      "score": 1,
      "secure_media_embed": {},
      "selftext": "",
      "stickied": false,
      "subreddit": "worldnews",
      "subreddit_id": "t5_2qh13",
      "thumbnail": "default",
      "title": "Apple Mac Technical Support Phone Number-1-800-506-9828 For Mac",
      "url": "http://applemactechsupportphonenumber.tumblr.com/"
    },
    {
      "author": "mtfyz",
      "author_created_utc": 1439344393,
      "author_flair_css_class": null,
      "author_flair_text": null,
      "author_fullname": "t2_phlwx",
      "created_utc": 1440377272,
      "domain": "youtube.com",
      "full_link": "https://www.reddit.com/r/worldnews/comments/3i56b0/a_great_commercial_from_apple_30_years_later/",
      "gilded": 0,
      "id": "3i56b0",
      "is_self": false,
      "media": {
        "oembed": {
          "author_name": "Mustafa Yazicioglu Creative Research",
          "author_url": "https://www.youtube.com/user/MustafaYazicioglu",
          "description": "30 Years Later - iPhone 44G",
          "height": 338,
          "html": "&lt;iframe class=\"embedly-embed\" src=\"//cdn.embedly.com/widgets/media.html?src=https%3A%2F%2Fwww.youtube.com%2Fembed%2FWgD2MgcGVwk%3Ffeature%3Doembed&amp;url=https%3A%2F%2Fwww.youtube.com%2Fwatch%3Fv%3DWgD2MgcGVwk&amp;image=https%3A%2F%2Fi.ytimg.com%2Fvi%2FWgD2MgcGVwk%2Fhqdefault.jpg&amp;key=2aa3c4d5f3de4f5b9120b660ad850dc9&amp;type=text%2Fhtml&amp;schema=youtube\" width=\"600\" height=\"338\" scrolling=\"no\" frameborder=\"0\" allowfullscreen&gt;&lt;/iframe&gt;",
          "provider_name": "YouTube",
          "provider_url": "https://www.youtube.com/",
          "thumbnail_height": 360,
          "thumbnail_url": "https://i.ytimg.com/vi/WgD2MgcGVwk/hqdefault.jpg",
          "thumbnail_width": 480,
          "title": "30 Years Later - iPhone 44G",
          "type": "video",
          "url": "http://www.youtube.com/watch?v=WgD2MgcGVwk",
          "version": "1.0",
          "width": 600
        },
        "type": "youtube.com"
      },
      "media_embed": {
        "content": "&lt;iframe class=\"embedly-embed\" src=\"//cdn.embedly.com/widgets/media.html?src=https%3A%2F%2Fwww.youtube.com%2Fembed%2FWgD2MgcGVwk%3Ffeature%3Doembed&amp;url=https%3A%2F%2Fwww.youtube.com%2Fwatch%3Fv%3DWgD2MgcGVwk&amp;image=https%3A%2F%2Fi.ytimg.com%2Fvi%2FWgD2MgcGVwk%2Fhqdefault.jpg&amp;key=2aa3c4d5f3de4f5b9120b660ad850dc9&amp;type=text%2Fhtml&amp;schema=youtube\" width=\"600\" height=\"338\" scrolling=\"no\" frameborder=\"0\" allowfullscreen&gt;&lt;/iframe&gt;",
        "height": 338,
        "scrolling": false,
        "width": 600
      },
      "num_comments": 1,
      "over_18": false,
      "permalink": "/r/worldnews/comments/3i56b0/a_great_commercial_from_apple_30_years_later/",
      "retrieved_on": 1440528748,
      "score": 1,
      "secure_media": {
        "oembed": {
          "author_name": "Mustafa Yazicioglu Creative Research",
          "author_url": "https://www.youtube.com/user/MustafaYazicioglu",
          "description": "30 Years Later - iPhone 44G",
          "height": 338,
          "html": "&lt;iframe class=\"embedly-embed\" src=\"https://cdn.embedly.com/widgets/media.html?src=https%3A%2F%2Fwww.youtube.com%2Fembed%2FWgD2MgcGVwk%3Ffeature%3Doembed&amp;url=https%3A%2F%2Fwww.youtube.com%2Fwatch%3Fv%3DWgD2MgcGVwk&amp;image=https%3A%2F%2Fi.ytimg.com%2Fvi%2FWgD2MgcGVwk%2Fhqdefault.jpg&amp;key=2aa3c4d5f3de4f5b9120b660ad850dc9&amp;type=text%2Fhtml&amp;schema=youtube\" width=\"600\" height=\"338\" scrolling=\"no\" frameborder=\"0\" allowfullscreen&gt;&lt;/iframe&gt;",
          "provider_name": "YouTube",
          "provider_url": "https://www.youtube.com/",
          "thumbnail_height": 360,
          "thumbnail_url": "https://i.embed.ly/1/image?url=https%3A%2F%2Fi.ytimg.com%2Fvi%2FWgD2MgcGVwk%2Fhqdefault.jpg&amp;key=b1e305db91cf4aa5a86b732cc9fffceb",
          "thumbnail_width": 480,
          "title": "30 Years Later - iPhone 44G",
          "type": "video",
          "url": "http://www.youtube.com/watch?v=WgD2MgcGVwk",
          "version": "1.0",
          "width": 600
        },
        "type": "youtube.com"
      },
      "secure_media_embed": {
        "content": "&lt;iframe class=\"embedly-embed\" src=\"https://cdn.embedly.com/widgets/media.html?src=https%3A%2F%2Fwww.youtube.com%2Fembed%2FWgD2MgcGVwk%3Ffeature%3Doembed&amp;url=https%3A%2F%2Fwww.youtube.com%2Fwatch%3Fv%3DWgD2MgcGVwk&amp;image=https%3A%2F%2Fi.ytimg.com%2Fvi%2FWgD2MgcGVwk%2Fhqdefault.jpg&amp;key=2aa3c4d5f3de4f5b9120b660ad850dc9&amp;type=text%2Fhtml&amp;schema=youtube\" width=\"600\" height=\"338\" scrolling=\"no\" frameborder=\"0\" allowfullscreen&gt;&lt;/iframe&gt;",
        "height": 338,
        "scrolling": false,
        "width": 600
      },
      "selftext": "",
      "stickied": false,
      "subreddit": "worldnews",
      "subreddit_id": "t5_2qh13",
      "thumbnail": "default",
      "title": "A Great Commercial From Apple! 30 Years Later - iPhone 44G",
      "url": "https://www.youtube.com/watch?v=WgD2MgcGVwk"
    },
    {
      "author": "Romek_himself",
      "author_created_utc": 1405761543,
      "author_flair_css_class": null,
      "author_flair_text": null,
      "author_fullname": "t2_hh0kw",
      "created_utc": 1440769727,
      "domain": "nbcnews.com",
      "full_link": "https://www.reddit.com/r/worldnews/comments/3iq5bz/pentagon_teams_up_with_apple_boeing_to_develop/",
      "gilded": 0,
      "id": "3iq5bz",
      "is_self": false,
      "media_embed": {},
      "num_comments": 2,
      "over_18": false,
      "permalink": "/r/worldnews/comments/3iq5bz/pentagon_teams_up_with_apple_boeing_to_develop/",
      "post_hint": "link",
      "preview": {
        "images": [
          {
            "id": "WFN_HbahVQ_lBKNeDM8UIyCX_JT9DFN5bz76YzlVZR0",
            "resolutions": [
              {
                "height": 72,
                "url": "https://i.redditmedia.com/2Nx-zNmJb8-r7YJnV4-AC1C2dw_FxtkudXorrG3KgmQ.jpg?fit=crop&amp;crop=faces%2Centropy&amp;arh=2&amp;w=108&amp;s=8be5973b4db86288d0d3964834a8c980",
                "width": 108
              },
              {
                "height": 144,
                "url": "https://i.redditmedia.com/2Nx-zNmJb8-r7YJnV4-AC1C2dw_FxtkudXorrG3KgmQ.jpg?fit=crop&amp;crop=faces%2Centropy&amp;arh=2&amp;w=216&amp;s=2a575959d3956f0a9c02bf5d497bad38",
                "width": 216
              },
              {
                "height": 213,
                "url": "https://i.redditmedia.com/2Nx-zNmJb8-r7YJnV4-AC1C2dw_FxtkudXorrG3KgmQ.jpg?fit=crop&amp;crop=faces%2Centropy&amp;arh=2&amp;w=320&amp;s=5d60c67b0de9615d31134aa43178cab3",
                "width": 320
              },
              {
                "height": 426,
                "url": "https://i.redditmedia.com/2Nx-zNmJb8-r7YJnV4-AC1C2dw_FxtkudXorrG3KgmQ.jpg?fit=crop&amp;crop=faces%2Centropy&amp;arh=2&amp;w=640&amp;s=d376ea31dfdf1b9cd86f2f26ef460e8b",
                "width": 640
              },
              {
                "height": 640,
                "url": "https://i.redditmedia.com/2Nx-zNmJb8-r7YJnV4-AC1C2dw_FxtkudXorrG3KgmQ.jpg?fit=crop&amp;crop=faces%2Centropy&amp;arh=2&amp;w=960&amp;s=9d7ebc0df2677d757dff28b03c28c8ba",
                "width": 960
              },
              {
                "height": 720,
                "url": "https://i.redditmedia.com/2Nx-zNmJb8-r7YJnV4-AC1C2dw_FxtkudXorrG3KgmQ.jpg?fit=crop&amp;crop=faces%2Centropy&amp;arh=2&amp;w=1080&amp;s=819be7c3d4fc29bd637a41395d50528a",
                "width": 1080
              }
            ],
            "source": {
              "height": 800,
              "url": "https://i.redditmedia.com/2Nx-zNmJb8-r7YJnV4-AC1C2dw_FxtkudXorrG3KgmQ.jpg?s=0d886d9ce380448b723be0f7ea5bfacc",
              "width": 1200
            },
            "variants": {}
          }
        ]
      },
      "retrieved_on": 1443148289,
      "score": 0,
      "secure_media_embed": {},
      "selftext": "",
      "stickied": false,
      "subreddit": "worldnews",
      "subreddit_id": "t5_2qh13",
      "thumbnail": "http://b.thumbs.redditmedia.com/ugdz2Nl1z-gOesJKZKrcJl94YQzHeBrznMZmMdVlvyU.jpg",
      "title": "Pentagon Teams up With Apple, Boeing to Develop Wearable Tech",
      "url": "http://www.nbcnews.com/tech/tech-news/pentagon-teams-apple-develop-wearable-tech-n417646"
    },
    {
      "author": "[deleted]",
      "author_flair_css_class": null,
      "author_flair_text": null,
      "created_utc": 1440602282,
      "domain": "ibtimes.com",
      "full_link": "https://www.reddit.com/r/worldnews/comments/3ih56n/best_buy_calls_apple_watch_iconic_will_roll_out/",
      "gilded": 0,
      "id": "3ih56n",
      "is_self": false,
      "link_flair_css_class": "normal",
      "link_flair_text": "Not Appropriate Subreddit",
      "media_embed": {},
      "num_comments": 0,
      "over_18": false,
      "permalink": "/r/worldnews/comments/3ih56n/best_buy_calls_apple_watch_iconic_will_roll_out/",
      "retrieved_on": 1443144037,
      "score": 0,
      "secure_media_embed": {},
      "selftext": "[deleted]",
      "stickied": false,
      "subreddit": "worldnews",
      "subreddit_id": "t5_2qh13",
      "thumbnail": "default",
      "title": "Best Buy Calls Apple Watch 'Iconic'; Will Roll Out Smartwatch To All 1,000 US Locations",
      "url": "http://www.ibtimes.com/best-buy-calls-apple-watch-iconic-will-roll-out-smartwatch-all-1000-us-locations-2069106"
    },
    {
      "author": "Sajidturri",
      "author_created_utc": 1436823224,
      "author_flair_css_class": null,
      "author_flair_text": null,
      "author_fullname": "t2_orx1m",
      "created_utc": 1439233966,
      "domain": "itechdunya.blogspot.co.uk",
      "full_link": "https://www.reddit.com/r/worldnews/comments/3ghzc6/is_it_game_over_for_apple/",
      "gilded": 0,
      "id": "3ghzc6",
      "is_self": false,
      "media_embed": {},
      "num_comments": 0,
      "over_18": false,
      "permalink": "/r/worldnews/comments/3ghzc6/is_it_game_over_for_apple/",
      "retrieved_on": 1440556861,
      "score": 0,
      "secure_media_embed": {},
      "selftext": "",
      "stickied": false,
      "subreddit": "worldnews",
      "subreddit_id": "t5_2qh13",
      "thumbnail": "default",
      "title": "Is It Game Over For Apple?",
      "url": "http://itechdunya.blogspot.co.uk/2015/08/is-it-game-over-for-apple.html"
    },
    {
      "author": "stefi9100",
      "author_created_utc": 1385410761,
      "author_flair_css_class": null,
      "author_flair_text": null,
      "author_fullname": "t2_e2jif",
      "created_utc": 1438954379,
      "domain": "9to5mac.com",
      "full_link": "https://www.reddit.com/r/worldnews/comments/3g4m8k/apple_spends_700kyear_on_keeping_ceo_tim_cook/",
      "gilded": 0,
      "id": "3g4m8k",
      "is_self": false,
      "media_embed": {},
      "num_comments": 1,
      "over_18": false,
      "permalink": "/r/worldnews/comments/3g4m8k/apple_spends_700kyear_on_keeping_ceo_tim_cook/",
      "retrieved_on": 1440563216,
      "score": 0,
      "secure_media_embed": {},
      "selftext": "",
      "stickied": false,
      "subreddit": "worldnews",
      "subreddit_id": "t5_2qh13",
      "thumbnail": "default",
      "title": "Apple spends $700K/year on keeping CEO Tim Cook safe \u2013 SEC filing",
      "url": "http://9to5mac.com/2015/08/07/tim-cook-security-costs-700k/"
    },
    {
      "author": "SublimeDeCalifornia",
      "author_flair_css_class": null,
      "author_flair_text": null,
      "created_utc": 1440782403,
      "domain": "macrumors.com",
      "full_link": "https://www.reddit.com/r/worldnews/comments/3iqyzm/apple_joins_massive_pentagon_partnership_to/",
      "gilded": 0,
      "id": "3iqyzm",
      "is_self": false,
      "media_embed": {},
      "num_comments": 1,
      "over_18": false,
      "permalink": "/r/worldnews/comments/3iqyzm/apple_joins_massive_pentagon_partnership_to/",
      "post_hint": "link",
      "preview": {
        "images": [
          {
            "id": "sv6q9Wmb5R-8qaE73_7vusoZznCv-mxYznmMCs1f9KQ",
            "resolutions": [
              {
                "height": 43,
                "url": "https://i.redditmedia.com/exoaXJYyo_MjpJHdzN8VYQ_i5BZWhEn7EXgwoBhgEQo.jpg?fit=crop&amp;crop=faces%2Centropy&amp;arh=2&amp;w=108&amp;s=c2e48f401e11a9b919cebb0c67743f3d",
                "width": 108
              },
              {
                "height": 87,
                "url": "https://i.redditmedia.com/exoaXJYyo_MjpJHdzN8VYQ_i5BZWhEn7EXgwoBhgEQo.jpg?fit=crop&amp;crop=faces%2Centropy&amp;arh=2&amp;w=216&amp;s=55781f0331e98e02b292125e40e298ae",
                "width": 216
              },
              {
                "height": 129,
                "url": "https://i.redditmedia.com/exoaXJYyo_MjpJHdzN8VYQ_i5BZWhEn7EXgwoBhgEQo.jpg?fit=crop&amp;crop=faces%2Centropy&amp;arh=2&amp;w=320&amp;s=c6b574cfaaa96c5abf270974bd31fd39",
                "width": 320
              },
              {
                "height": 258,
                "url": "https://i.redditmedia.com/exoaXJYyo_MjpJHdzN8VYQ_i5BZWhEn7EXgwoBhgEQo.jpg?fit=crop&amp;crop=faces%2Centropy&amp;arh=2&amp;w=640&amp;s=f4d5251d94501de3938b493ba08329b4",
                "width": 640
              },
              {
                "height": 387,
                "url": "https://i.redditmedia.com/exoaXJYyo_MjpJHdzN8VYQ_i5BZWhEn7EXgwoBhgEQo.jpg?fit=crop&amp;crop=faces%2Centropy&amp;arh=2&amp;w=960&amp;s=b556278dd9d00d40bf57582882102c42",
                "width": 960
              },
              {
                "height": 435,
                "url": "https://i.redditmedia.com/exoaXJYyo_MjpJHdzN8VYQ_i5BZWhEn7EXgwoBhgEQo.jpg?fit=crop&amp;crop=faces%2Centropy&amp;arh=2&amp;w=1080&amp;s=3f0ba704ef5f389f0c78448841b2de48",
                "width": 1080
              }
            ],
            "source": {
              "height": 540,
              "url": "https://i.redditmedia.com/exoaXJYyo_MjpJHdzN8VYQ_i5BZWhEn7EXgwoBhgEQo.jpg?s=28fa2bef2068bb02d225a603de6b97fe",
              "width": 1338
            },
            "variants": {}
          }
        ]
      },
      "retrieved_on": 1443148677,
      "score": 0,
      "secure_media_embed": {},
      "selftext": "",
      "stickied": false,
      "subreddit": "worldnews",
      "subreddit_id": "t5_2qh13",
      "thumbnail": "http://b.thumbs.redditmedia.com/lpe4KCjZj3lyKTjtjAjiM-3f8LZg4HTy3XixilSxNsg.jpg",
      "title": "Apple Joins Massive Pentagon Partnership to Develop High-Tech Military Wearables",
      "url": "http://www.macrumors.com/2015/08/28/apple-joins-pentagon-wearables/"
    }
  ]
}